{
    "letters": "WEIPRUV",
    "generation_info": {
        "path": "word_lists/TWL06.txt",
        "min_word_length": 4,
        "total_letter_count": 7,
        "min_word_count": 30,
        "max_word_count": 50,
        "min_total_score": 80,
        "max_total_score": 120,
        "count_pangrams": 1,
        "manual_puzzle": false
    },
    "total_score": 88,
    "word_count": 32,
    "pangram_count": 1,
    "pangram_list": [
        "PURVIEW"
    ],
    "word_list": [
        {
            "word": "EWER",
            "score": 1,
            "pangram": false
        },
        {
            "word": "PEEWEE",
            "score": 3,
            "pangram": false
        },
        {
            "word": "PEWEE",
            "score": 2,
            "pangram": false
        },
        {
            "word": "PREREVIEW",
            "score": 6,
            "pangram": false
        },
        {
            "word": "PREVIEW",
            "score": 4,
            "pangram": false
        },
        {
            "word": "PREVIEWER",
            "score": 6,
            "pangram": false
        },
        {
            "word": "PREWIRE",
            "score": 4,
            "pangram": false
        },
        {
            "word": "PURVIEW",
            "score": 4,
            "pangram": true
        },
        {
            "word": "REREVIEW",
            "score": 5,
            "pangram": false
        },
        {
            "word": "REVIEW",
            "score": 3,
            "pangram": false
        },
        {
            "word": "REVIEWER",
            "score": 5,
            "pangram": false
        },
        {
            "word": "REWIRE",
            "score": 3,
            "pangram": false
        },
        {
            "word": "VIEW",
            "score": 1,
            "pangram": false
        },
        {
            "word": "VIEWER",
            "score": 3,
            "pangram": false
        },
        {
            "word": "VIEWIER",
            "score": 4,
            "pangram": false
        },
        {
            "word": "WEEP",
            "score": 1,
            "pangram": false
        },
        {
            "word": "WEEPER",
            "score": 3,
            "pangram": false
        },
        {
            "word": "WEEPIE",
            "score": 3,
            "pangram": false
        },
        {
            "word": "WEEPIER",
            "score": 4,
            "pangram": false
        },
        {
            "word": "WEER",
            "score": 1,
            "pangram": false
        },
        {
            "word": "WEEVER",
            "score": 3,
            "pangram": false
        },
        {
            "word": "WEEWEE",
            "score": 3,
            "pangram": false
        },
        {
            "word": "WEIR",
            "score": 1,
            "pangram": false
        },
        {
            "word": "WERE",
            "score": 1,
            "pangram": false
        },
        {
            "word": "WIPE",
            "score": 1,
            "pangram": false
        },
        {
            "word": "WIPER",
            "score": 2,
            "pangram": false
        },
        {
            "word": "WIRE",
            "score": 1,
            "pangram": false
        },
        {
            "word": "WIRER",
            "score": 2,
            "pangram": false
        },
        {
            "word": "WIRIER",
            "score": 3,
            "pangram": false
        },
        {
            "word": "WIVE",
            "score": 1,
            "pangram": false
        },
        {
            "word": "WIVER",
            "score": 2,
            "pangram": false
        },
        {
            "word": "WRIER",
            "score": 2,
            "pangram": false
        }
    ]
}