{
    "letters": "YAILMRX",
    "generation_info": {
        "path": "word_lists/TWL06.txt",
        "min_word_length": 4,
        "total_letter_count": 7,
        "min_word_count": 30,
        "max_word_count": 50,
        "min_total_score": 80,
        "max_total_score": 120,
        "count_pangrams": 1,
        "manual_puzzle": false
    },
    "total_score": 102,
    "word_count": 42,
    "pangram_count": 1,
    "pangram_list": [
        "MAXILLARY"
    ],
    "word_list": [
        {
            "word": "AIRILY",
            "score": 3,
            "pangram": false
        },
        {
            "word": "AIRY",
            "score": 1,
            "pangram": false
        },
        {
            "word": "ALARY",
            "score": 2,
            "pangram": false
        },
        {
            "word": "ALIYA",
            "score": 2,
            "pangram": false
        },
        {
            "word": "ALLAY",
            "score": 2,
            "pangram": false
        },
        {
            "word": "ALLY",
            "score": 1,
            "pangram": false
        },
        {
            "word": "ALLYL",
            "score": 2,
            "pangram": false
        },
        {
            "word": "AMYL",
            "score": 1,
            "pangram": false
        },
        {
            "word": "ARIARY",
            "score": 3,
            "pangram": false
        },
        {
            "word": "ARMILLARY",
            "score": 6,
            "pangram": false
        },
        {
            "word": "ARMY",
            "score": 1,
            "pangram": false
        },
        {
            "word": "ARRAY",
            "score": 2,
            "pangram": false
        },
        {
            "word": "ARRAYAL",
            "score": 4,
            "pangram": false
        },
        {
            "word": "ARYL",
            "score": 1,
            "pangram": false
        },
        {
            "word": "AXIALLY",
            "score": 4,
            "pangram": false
        },
        {
            "word": "AXILLARY",
            "score": 5,
            "pangram": false
        },
        {
            "word": "ILLY",
            "score": 1,
            "pangram": false
        },
        {
            "word": "IMMY",
            "score": 1,
            "pangram": false
        },
        {
            "word": "LAXLY",
            "score": 2,
            "pangram": false
        },
        {
            "word": "LILY",
            "score": 1,
            "pangram": false
        },
        {
            "word": "LIMY",
            "score": 1,
            "pangram": false
        },
        {
            "word": "MALMY",
            "score": 2,
            "pangram": false
        },
        {
            "word": "MAMMARY",
            "score": 4,
            "pangram": false
        },
        {
            "word": "MAMMILLARY",
            "score": 7,
            "pangram": false
        },
        {
            "word": "MAMMY",
            "score": 2,
            "pangram": false
        },
        {
            "word": "MARLY",
            "score": 2,
            "pangram": false
        },
        {
            "word": "MARRY",
            "score": 2,
            "pangram": false
        },
        {
            "word": "MAXILLARY",
            "score": 6,
            "pangram": true
        },
        {
            "word": "MAXIMALLY",
            "score": 6,
            "pangram": false
        },
        {
            "word": "MAYA",
            "score": 1,
            "pangram": false
        },
        {
            "word": "MILIARY",
            "score": 4,
            "pangram": false
        },
        {
            "word": "MILLIARY",
            "score": 5,
            "pangram": false
        },
        {
            "word": "MIRY",
            "score": 1,
            "pangram": false
        },
        {
            "word": "MYLAR",
            "score": 2,
            "pangram": false
        },
        {
            "word": "RALLY",
            "score": 2,
            "pangram": false
        },
        {
            "word": "RAMMY",
            "score": 2,
            "pangram": false
        },
        {
            "word": "RAYA",
            "score": 1,
            "pangram": false
        },
        {
            "word": "RIMY",
            "score": 1,
            "pangram": false
        },
        {
            "word": "RIYAL",
            "score": 2,
            "pangram": false
        },
        {
            "word": "XYLYL",
            "score": 2,
            "pangram": false
        },
        {
            "word": "YILL",
            "score": 1,
            "pangram": false
        },
        {
            "word": "YIRR",
            "score": 1,
            "pangram": false
        }
    ]
}