{
    "letters": "MABELNT",
    "generation_info": {
        "path": "word_lists/scowl.txt",
        "min_word_length": 4,
        "total_letter_count": 7,
        "min_word_count": 25,
        "max_word_count": 50,
        "min_total_score": 60,
        "max_total_score": 240,
        "cap_plurals": true,
        "max_plurals": 3,
        "cap_gerunds": true,
        "max_gerunds": 5,
        "count_pangrams": 1,
        "manual_puzzle": true
    },
    "total_score": 112,
    "word_count": 49,
    "pangram_count": 1,
    "pangram_list": [
        "LAMENTABLE"
    ],
    "word_list": [
        {
            "word": "AMBLE",
            "score": 2,
            "pangram": false
        },
        {
            "word": "AMEN",
            "score": 1,
            "pangram": false
        },
        {
            "word": "AMENABLE",
            "score": 5,
            "pangram": false
        },
        {
            "word": "BALM",
            "score": 1,
            "pangram": false
        },
        {
            "word": "BEAM",
            "score": 1,
            "pangram": false
        },
        {
            "word": "BLAME",
            "score": 2,
            "pangram": false
        },
        {
            "word": "ELEMENT",
            "score": 4,
            "pangram": false
        },
        {
            "word": "ELEMENTAL",
            "score": 6,
            "pangram": false
        },
        {
            "word": "EMANATE",
            "score": 4,
            "pangram": false
        },
        {
            "word": "EMBALM",
            "score": 3,
            "pangram": false
        },
        {
            "word": "EMBLEM",
            "score": 3,
            "pangram": false
        },
        {
            "word": "ENAMEL",
            "score": 3,
            "pangram": false
        },
        {
            "word": "ENEMA",
            "score": 2,
            "pangram": false
        },
        {
            "word": "LAMB",
            "score": 1,
            "pangram": false
        },
        {
            "word": "LAME",
            "score": 1,
            "pangram": false
        },
        {
            "word": "LAMENT",
            "score": 3,
            "pangram": false
        },
        {
            "word": "LAMENTABLE",
            "score": 7,
            "pangram": true
        },
        {
            "word": "LEMME",
            "score": 2,
            "pangram": false
        },
        {
            "word": "LLAMA",
            "score": 2,
            "pangram": false
        },
        {
            "word": "MALE",
            "score": 1,
            "pangram": false
        },
        {
            "word": "MALL",
            "score": 1,
            "pangram": false
        },
        {
            "word": "MALLEABLE",
            "score": 6,
            "pangram": false
        },
        {
            "word": "MALLET",
            "score": 3,
            "pangram": false
        },
        {
            "word": "MALT",
            "score": 1,
            "pangram": false
        },
        {
            "word": "MAMA",
            "score": 1,
            "pangram": false
        },
        {
            "word": "MAMMA",
            "score": 2,
            "pangram": false
        },
        {
            "word": "MAMMAL",
            "score": 3,
            "pangram": false
        },
        {
            "word": "MANE",
            "score": 1,
            "pangram": false
        },
        {
            "word": "MANTEL",
            "score": 3,
            "pangram": false
        },
        {
            "word": "MANTLE",
            "score": 3,
            "pangram": false
        },
        {
            "word": "MATE",
            "score": 1,
            "pangram": false
        },
        {
            "word": "MATT",
            "score": 1,
            "pangram": false
        },
        {
            "word": "MATTE",
            "score": 2,
            "pangram": false
        },
        {
            "word": "MEAL",
            "score": 1,
            "pangram": false
        },
        {
            "word": "MEAN",
            "score": 1,
            "pangram": false
        },
        {
            "word": "MEANT",
            "score": 2,
            "pangram": false
        },
        {
            "word": "MEAT",
            "score": 1,
            "pangram": false
        },
        {
            "word": "MEET",
            "score": 1,
            "pangram": false
        },
        {
            "word": "MELT",
            "score": 1,
            "pangram": false
        },
        {
            "word": "MENTAL",
            "score": 3,
            "pangram": false
        },
        {
            "word": "METAL",
            "score": 2,
            "pangram": false
        },
        {
            "word": "METE",
            "score": 1,
            "pangram": false
        },
        {
            "word": "METTLE",
            "score": 3,
            "pangram": false
        },
        {
            "word": "NAME",
            "score": 1,
            "pangram": false
        },
        {
            "word": "TAME",
            "score": 1,
            "pangram": false
        },
        {
            "word": "TEAM",
            "score": 1,
            "pangram": false
        },
        {
            "word": "TEAMMATE",
            "score": 5,
            "pangram": false
        },
        {
            "word": "TEEM",
            "score": 1,
            "pangram": false
        },
        {
            "word": "TENEMENT",
            "score": 5,
            "pangram": false
        }
    ]
}