{
    "letters": "OABCHKU",
    "generation_info": {
        "path": "word_lists/TWL06.txt",
        "min_word_length": 4,
        "total_letter_count": 7,
        "min_word_count": 30,
        "max_word_count": 50,
        "min_total_score": 80,
        "max_total_score": 120,
        "count_pangrams": 1,
        "manual_puzzle": true
    },
    "total_score": 95,
    "word_count": 48,
    "pangram_count": 1,
    "pangram_list": [
        "CHABOUK"
    ],
    "word_list": [
        {
            "word": "ACHOO",
            "score": 2,
            "pangram": false
        },
        {
            "word": "ACOCK",
            "score": 2,
            "pangram": false
        },
        {
            "word": "AHCHOO",
            "score": 3,
            "pangram": false
        },
        {
            "word": "BABOO",
            "score": 2,
            "pangram": false
        },
        {
            "word": "BAOBAB",
            "score": 3,
            "pangram": false
        },
        {
            "word": "BOCK",
            "score": 1,
            "pangram": false
        },
        {
            "word": "BOHO",
            "score": 1,
            "pangram": false
        },
        {
            "word": "BOOB",
            "score": 1,
            "pangram": false
        },
        {
            "word": "BOOBOO",
            "score": 3,
            "pangram": false
        },
        {
            "word": "BOOCOO",
            "score": 3,
            "pangram": false
        },
        {
            "word": "BOOHOO",
            "score": 3,
            "pangram": false
        },
        {
            "word": "BOOK",
            "score": 1,
            "pangram": false
        },
        {
            "word": "BOOKOO",
            "score": 3,
            "pangram": false
        },
        {
            "word": "BOUBOU",
            "score": 3,
            "pangram": false
        },
        {
            "word": "BUBO",
            "score": 1,
            "pangram": false
        },
        {
            "word": "BUCKO",
            "score": 2,
            "pangram": false
        },
        {
            "word": "CABOB",
            "score": 2,
            "pangram": false
        },
        {
            "word": "CACAO",
            "score": 2,
            "pangram": false
        },
        {
            "word": "CACHOU",
            "score": 3,
            "pangram": false
        },
        {
            "word": "CHABOUK",
            "score": 4,
            "pangram": true
        },
        {
            "word": "CHAO",
            "score": 1,
            "pangram": false
        },
        {
            "word": "CHOCK",
            "score": 2,
            "pangram": false
        },
        {
            "word": "CHOOK",
            "score": 2,
            "pangram": false
        },
        {
            "word": "COACH",
            "score": 2,
            "pangram": false
        },
        {
            "word": "COBB",
            "score": 1,
            "pangram": false
        },
        {
            "word": "COCA",
            "score": 1,
            "pangram": false
        },
        {
            "word": "COCK",
            "score": 1,
            "pangram": false
        },
        {
            "word": "COCO",
            "score": 1,
            "pangram": false
        },
        {
            "word": "COCOA",
            "score": 2,
            "pangram": false
        },
        {
            "word": "COHO",
            "score": 1,
            "pangram": false
        },
        {
            "word": "COOCH",
            "score": 2,
            "pangram": false
        },
        {
            "word": "COOCOO",
            "score": 3,
            "pangram": false
        },
        {
            "word": "COOK",
            "score": 1,
            "pangram": false
        },
        {
            "word": "COOKBOOK",
            "score": 5,
            "pangram": false
        },
        {
            "word": "COUCH",
            "score": 2,
            "pangram": false
        },
        {
            "word": "CUCKOO",
            "score": 3,
            "pangram": false
        },
        {
            "word": "HABOOB",
            "score": 3,
            "pangram": false
        },
        {
            "word": "HOBO",
            "score": 1,
            "pangram": false
        },
        {
            "word": "HOCK",
            "score": 1,
            "pangram": false
        },
        {
            "word": "HOKKU",
            "score": 2,
            "pangram": false
        },
        {
            "word": "HOOCH",
            "score": 2,
            "pangram": false
        },
        {
            "word": "HOOK",
            "score": 1,
            "pangram": false
        },
        {
            "word": "HOOKA",
            "score": 2,
            "pangram": false
        },
        {
            "word": "HOOKAH",
            "score": 3,
            "pangram": false
        },
        {
            "word": "KABOB",
            "score": 2,
            "pangram": false
        },
        {
            "word": "KOBO",
            "score": 1,
            "pangram": false
        },
        {
            "word": "KOOK",
            "score": 1,
            "pangram": false
        },
        {
            "word": "OUCH",
            "score": 1,
            "pangram": false
        }
    ]
}