{
    "letters": "PCDEHIN",
    "generation_info": {
        "path": "word_lists/scowl.txt",
        "min_word_length": 4,
        "total_letter_count": 7,
        "min_word_count": 25,
        "max_word_count": 50,
        "min_total_score": 60,
        "max_total_score": 240,
        "cap_plurals": true,
        "max_plurals": 3,
        "cap_gerunds": true,
        "max_gerunds": 5,
        "count_pangrams": 1,
        "manual_puzzle": true
    },
    "total_score": 95,
    "word_count": 32,
    "pangram_count": 1,
    "pangram_list": [
        "PINCHED"
    ],
    "word_list": [
        {
            "word": "CHEEP",
            "score": 2,
            "pangram": false
        },
        {
            "word": "CHEEPED",
            "score": 4,
            "pangram": false
        },
        {
            "word": "CHIP",
            "score": 1,
            "pangram": false
        },
        {
            "word": "CHIPPED",
            "score": 4,
            "pangram": false
        },
        {
            "word": "DEEP",
            "score": 1,
            "pangram": false
        },
        {
            "word": "DEEPEN",
            "score": 3,
            "pangram": false
        },
        {
            "word": "DEEPENED",
            "score": 5,
            "pangram": false
        },
        {
            "word": "DEPEND",
            "score": 3,
            "pangram": false
        },
        {
            "word": "DEPENDED",
            "score": 5,
            "pangram": false
        },
        {
            "word": "DEPENDENCE",
            "score": 7,
            "pangram": false
        },
        {
            "word": "DIPPED",
            "score": 3,
            "pangram": false
        },
        {
            "word": "EPIC",
            "score": 1,
            "pangram": false
        },
        {
            "word": "HIPPED",
            "score": 3,
            "pangram": false
        },
        {
            "word": "HIPPIE",
            "score": 3,
            "pangram": false
        },
        {
            "word": "INDEPENDENCE",
            "score": 9,
            "pangram": false
        },
        {
            "word": "NIPPED",
            "score": 3,
            "pangram": false
        },
        {
            "word": "PEEP",
            "score": 1,
            "pangram": false
        },
        {
            "word": "PEEPED",
            "score": 3,
            "pangram": false
        },
        {
            "word": "PENCE",
            "score": 2,
            "pangram": false
        },
        {
            "word": "PENDED",
            "score": 3,
            "pangram": false
        },
        {
            "word": "PENNED",
            "score": 3,
            "pangram": false
        },
        {
            "word": "PEPPED",
            "score": 3,
            "pangram": false
        },
        {
            "word": "PICNIC",
            "score": 3,
            "pangram": false
        },
        {
            "word": "PIECE",
            "score": 2,
            "pangram": false
        },
        {
            "word": "PIECED",
            "score": 3,
            "pangram": false
        },
        {
            "word": "PINCH",
            "score": 2,
            "pangram": false
        },
        {
            "word": "PINCHED",
            "score": 4,
            "pangram": true
        },
        {
            "word": "PINE",
            "score": 1,
            "pangram": false
        },
        {
            "word": "PINED",
            "score": 2,
            "pangram": false
        },
        {
            "word": "PINNED",
            "score": 3,
            "pangram": false
        },
        {
            "word": "PIPE",
            "score": 1,
            "pangram": false
        },
        {
            "word": "PIPED",
            "score": 2,
            "pangram": false
        }
    ]
}