{
    "letters": "UAEGNSV",
    "generation_info": {
        "path": "word_lists/scowl.txt",
        "min_word_length": 4,
        "total_letter_count": 7,
        "min_word_count": 30,
        "max_word_count": 50,
        "min_total_score": 80,
        "max_total_score": 120,
        "count_pangrams": 1,
        "manual_puzzle": false
    },
    "total_score": 85,
    "word_count": 35,
    "pangram_count": 1,
    "pangram_list": [
        "VAGUENESS"
    ],
    "word_list": [
        {
            "word": "ANUS",
            "score": 1,
            "pangram": false
        },
        {
            "word": "ANUSES",
            "score": 3,
            "pangram": false
        },
        {
            "word": "AVENUE",
            "score": 3,
            "pangram": false
        },
        {
            "word": "AVENUES",
            "score": 4,
            "pangram": false
        },
        {
            "word": "ENSUE",
            "score": 2,
            "pangram": false
        },
        {
            "word": "ENSUES",
            "score": 3,
            "pangram": false
        },
        {
            "word": "GAUGE",
            "score": 2,
            "pangram": false
        },
        {
            "word": "GAUGES",
            "score": 3,
            "pangram": false
        },
        {
            "word": "GENUS",
            "score": 2,
            "pangram": false
        },
        {
            "word": "GNUS",
            "score": 1,
            "pangram": false
        },
        {
            "word": "GUESS",
            "score": 2,
            "pangram": false
        },
        {
            "word": "GUESSES",
            "score": 4,
            "pangram": false
        },
        {
            "word": "GUNS",
            "score": 1,
            "pangram": false
        },
        {
            "word": "NAUSEA",
            "score": 3,
            "pangram": false
        },
        {
            "word": "NUNS",
            "score": 1,
            "pangram": false
        },
        {
            "word": "SAUNA",
            "score": 2,
            "pangram": false
        },
        {
            "word": "SAUNAS",
            "score": 3,
            "pangram": false
        },
        {
            "word": "SAUSAGE",
            "score": 4,
            "pangram": false
        },
        {
            "word": "SAUSAGES",
            "score": 5,
            "pangram": false
        },
        {
            "word": "SNUG",
            "score": 1,
            "pangram": false
        },
        {
            "word": "SNUGS",
            "score": 2,
            "pangram": false
        },
        {
            "word": "SUAVE",
            "score": 2,
            "pangram": false
        },
        {
            "word": "SUES",
            "score": 1,
            "pangram": false
        },
        {
            "word": "SUNG",
            "score": 1,
            "pangram": false
        },
        {
            "word": "SUNS",
            "score": 1,
            "pangram": false
        },
        {
            "word": "UNEVEN",
            "score": 3,
            "pangram": false
        },
        {
            "word": "UNSEEN",
            "score": 3,
            "pangram": false
        },
        {
            "word": "UNSUNG",
            "score": 3,
            "pangram": false
        },
        {
            "word": "USAGE",
            "score": 2,
            "pangram": false
        },
        {
            "word": "USAGES",
            "score": 3,
            "pangram": false
        },
        {
            "word": "USES",
            "score": 1,
            "pangram": false
        },
        {
            "word": "VAGUE",
            "score": 2,
            "pangram": false
        },
        {
            "word": "VAGUENESS",
            "score": 6,
            "pangram": true
        },
        {
            "word": "VENUE",
            "score": 2,
            "pangram": false
        },
        {
            "word": "VENUES",
            "score": 3,
            "pangram": false
        }
    ]
}